{
	"swagger": "2.0",
	"info": {
		"title": "Iuf Junia API"
	},
	"paths": {
		"/competitions": {
			"post": {
				"description": "Creates a competition",
				"operationId": "competition-create",
				"parameters": [
					{
						"name": "body",
						"in": "body",
						"required": true,
						"description": "The new competition",
						"schema": {
							"$ref": "#/definitions/WritableCompetition"
						}
					}
				],
				"responses": {
					"201": {
						"description": "competition created"
					}
				},
				"tags": [
					"iuf.junia"
				]
			},
			"get": {
				"description": "List all competitions",
				"operationId": "competition-list",
				"responses": {
					"200": {
						"description": "Array of competitions",
						"schema": {
							"$ref": "#/definitions/PagedCompetitions"
						}
					}
				},
				"tags": [
					"iuf.junia"
				]
			}
		},
		"/competitions/{id}": {
			"get": {
				"description": "Reads a competition",
				"operationId": "competition-read",
				"parameters": [
					{
						"name": "id",
						"in": "path",
						"required": true,
						"description": "The competition id",
						"type": "integer"
					}
				],
				"responses": {
					"200": {
						"description": "gets the competition",
						"schema": {
							"$ref": "#/definitions/Competition"
						}
					},
					"400": {
						"description": "Invalid ID supplied"
					},
					"404": {
						"description": "No competition found"
					}
				},
				"tags": [
					"iuf.junia"
				]
			},
			"patch": {
				"description": "Updates a competition",
				"operationId": "competition-update",
				"parameters": [
					{
						"name": "id",
						"in": "path",
						"required": true,
						"description": "The competition id",
						"type": "integer"
					}
				],
				"responses": {
					"200": {
						"description": "competition updated",
						"schema": {
							"$ref": "#/definitions/Competition"
						}
					},
					"400": {
						"description": "Invalid ID supplied"
					},
					"404": {
						"description": "No competition found"
					}
				},
				"tags": [
					"iuf.junia"
				]
			},
			"delete": {
				"description": "Deletes a competition",
				"operationId": "competition-delete",
				"parameters": [
					{
						"name": "id",
						"in": "path",
						"required": true,
						"description": "The competition id",
						"type": "integer"
					}
				],
				"responses": {
					"204": {
						"description": "competition deleted"
					},
					"400": {
						"description": "Invalid ID supplied"
					},
					"404": {
						"description": "No competition found"
					}
				},
				"tags": [
					"iuf.junia"
				]
			}
		},
		"/startgroups": {
			"post": {
				"description": "Creates a startgroup",
				"operationId": "startgroup-create",
				"parameters": [
					{
						"name": "body",
						"in": "body",
						"required": true,
						"description": "The new startgroup",
						"schema": {
							"$ref": "#/definitions/WritableStartgroup"
						}
					}
				],
				"responses": {
					"201": {
						"description": "startgroup created"
					}
				},
				"tags": [
					"iuf.junia"
				]
			},
			"get": {
				"description": "List all startgroups",
				"operationId": "startgroup-list",
				"responses": {
					"200": {
						"description": "Array of startgroups",
						"schema": {
							"$ref": "#/definitions/PagedStartgroups"
						}
					}
				},
				"tags": [
					"iuf.junia"
				]
			}
		},
		"/startgroups/{id}": {
			"get": {
				"description": "Reads a startgroup",
				"operationId": "startgroup-read",
				"parameters": [
					{
						"name": "id",
						"in": "path",
						"required": true,
						"description": "The startgroup id",
						"type": "integer"
					}
				],
				"responses": {
					"200": {
						"description": "gets the startgroup",
						"schema": {
							"$ref": "#/definitions/Startgroup"
						}
					},
					"400": {
						"description": "Invalid ID supplied"
					},
					"404": {
						"description": "No startgroup found"
					}
				},
				"tags": [
					"iuf.junia"
				]
			},
			"patch": {
				"description": "Updates a startgroup",
				"operationId": "startgroup-update",
				"parameters": [
					{
						"name": "id",
						"in": "path",
						"required": true,
						"description": "The startgroup id",
						"type": "integer"
					}
				],
				"responses": {
					"200": {
						"description": "startgroup updated",
						"schema": {
							"$ref": "#/definitions/Startgroup"
						}
					},
					"400": {
						"description": "Invalid ID supplied"
					},
					"404": {
						"description": "No startgroup found"
					}
				},
				"tags": [
					"iuf.junia"
				]
			},
			"delete": {
				"description": "Deletes a startgroup",
				"operationId": "startgroup-delete",
				"parameters": [
					{
						"name": "id",
						"in": "path",
						"required": true,
						"description": "The startgroup id",
						"type": "integer"
					}
				],
				"responses": {
					"204": {
						"description": "startgroup deleted"
					},
					"400": {
						"description": "Invalid ID supplied"
					},
					"404": {
						"description": "No startgroup found"
					}
				},
				"tags": [
					"iuf.junia"
				]
			}
		},
		"/startgroups/{id}/relationship/competition": {
			"get": {
				"description": "Reads the relationship of startgroup to competition",
				"operationId": "startgroup-to-competition-relationship-read",
				"parameters": [
					{
						"name": "id",
						"in": "path",
						"required": true,
						"description": "The startgroup id",
						"type": "integer"
					}
				],
				"responses": {
					"400": {
						"description": "Invalid ID supplied"
					},
					"404": {
						"description": "No startgroup found"
					}
				},
				"tags": [
					"iuf.junia"
				]
			},
			"patch": {
				"description": "Updates the relationship of startgroup to competition",
				"operationId": "startgroup-to-competition-relationship-update",
				"parameters": [
					{
						"name": "id",
						"in": "path",
						"required": true,
						"description": "The startgroup id",
						"type": "integer"
					}
				],
				"responses": {
					"400": {
						"description": "Invalid ID supplied"
					},
					"404": {
						"description": "No startgroup found"
					}
				},
				"tags": [
					"iuf.junia"
				]
			}
		},
		"/startgroups/{id}/relationship/event": {
			"get": {
				"description": "Reads the relationship of startgroup to event",
				"operationId": "startgroup-to-event-relationship-read",
				"parameters": [
					{
						"name": "id",
						"in": "path",
						"required": true,
						"description": "The startgroup id",
						"type": "integer"
					}
				],
				"responses": {
					"400": {
						"description": "Invalid ID supplied"
					},
					"404": {
						"description": "No startgroup found"
					}
				},
				"tags": [
					"iuf.junia"
				]
			},
			"patch": {
				"description": "Updates the relationship of startgroup to event",
				"operationId": "startgroup-to-event-relationship-update",
				"parameters": [
					{
						"name": "id",
						"in": "path",
						"required": true,
						"description": "The startgroup id",
						"type": "integer"
					}
				],
				"responses": {
					"400": {
						"description": "Invalid ID supplied"
					},
					"404": {
						"description": "No startgroup found"
					}
				},
				"tags": [
					"iuf.junia"
				]
			}
		},
		"/routines": {
			"post": {
				"description": "Creates a routine",
				"operationId": "routine-create",
				"parameters": [
					{
						"name": "body",
						"in": "body",
						"required": true,
						"description": "The new routine",
						"schema": {
							"$ref": "#/definitions/WritableRoutine"
						}
					}
				],
				"responses": {
					"201": {
						"description": "routine created"
					}
				},
				"tags": [
					"iuf.junia"
				]
			},
			"get": {
				"description": "List all routines",
				"operationId": "routine-list",
				"responses": {
					"200": {
						"description": "Array of routines",
						"schema": {
							"$ref": "#/definitions/PagedRoutines"
						}
					}
				},
				"tags": [
					"iuf.junia"
				]
			}
		},
		"/routines/{id}": {
			"get": {
				"description": "Reads a routine",
				"operationId": "routine-read",
				"parameters": [
					{
						"name": "id",
						"in": "path",
						"required": true,
						"description": "The routine id",
						"type": "integer"
					}
				],
				"responses": {
					"200": {
						"description": "gets the routine",
						"schema": {
							"$ref": "#/definitions/Routine"
						}
					},
					"400": {
						"description": "Invalid ID supplied"
					},
					"404": {
						"description": "No routine found"
					}
				},
				"tags": [
					"iuf.junia"
				]
			},
			"patch": {
				"description": "Updates a routine",
				"operationId": "routine-update",
				"parameters": [
					{
						"name": "id",
						"in": "path",
						"required": true,
						"description": "The routine id",
						"type": "integer"
					}
				],
				"responses": {
					"200": {
						"description": "routine updated",
						"schema": {
							"$ref": "#/definitions/Routine"
						}
					},
					"400": {
						"description": "Invalid ID supplied"
					},
					"404": {
						"description": "No routine found"
					}
				},
				"tags": [
					"iuf.junia"
				]
			},
			"delete": {
				"description": "Deletes a routine",
				"operationId": "routine-delete",
				"parameters": [
					{
						"name": "id",
						"in": "path",
						"required": true,
						"description": "The routine id",
						"type": "integer"
					}
				],
				"responses": {
					"204": {
						"description": "routine deleted"
					},
					"400": {
						"description": "Invalid ID supplied"
					},
					"404": {
						"description": "No routine found"
					}
				},
				"tags": [
					"iuf.junia"
				]
			}
		},
		"/routines/{id}/relationship/startgroup": {
			"get": {
				"description": "Reads the relationship of routine to startgroup",
				"operationId": "routine-to-startgroup-relationship-read",
				"parameters": [
					{
						"name": "id",
						"in": "path",
						"required": true,
						"description": "The routine id",
						"type": "integer"
					}
				],
				"responses": {
					"400": {
						"description": "Invalid ID supplied"
					},
					"404": {
						"description": "No routine found"
					}
				},
				"tags": [
					"iuf.junia"
				]
			},
			"patch": {
				"description": "Updates the relationship of routine to startgroup",
				"operationId": "routine-to-startgroup-relationship-update",
				"parameters": [
					{
						"name": "id",
						"in": "path",
						"required": true,
						"description": "The routine id",
						"type": "integer"
					}
				],
				"responses": {
					"400": {
						"description": "Invalid ID supplied"
					},
					"404": {
						"description": "No routine found"
					}
				},
				"tags": [
					"iuf.junia"
				]
			}
		},
		"/routines/{id}/relationship/performance_statistics": {
			"get": {
				"description": "Reads the relationship of routine to performance_statistics",
				"operationId": "routine-to-performance_statistics-relationship-read",
				"parameters": [
					{
						"name": "id",
						"in": "path",
						"required": true,
						"description": "The routine id",
						"type": "integer"
					}
				],
				"responses": {
					"400": {
						"description": "Invalid ID supplied"
					},
					"404": {
						"description": "No routine found"
					}
				},
				"tags": [
					"iuf.junia"
				]
			},
			"patch": {
				"description": "Updates the relationship of routine to performance_statistics",
				"operationId": "routine-to-performance_statistics-relationship-update",
				"parameters": [
					{
						"name": "id",
						"in": "path",
						"required": true,
						"description": "The routine id",
						"type": "integer"
					}
				],
				"responses": {
					"400": {
						"description": "Invalid ID supplied"
					},
					"404": {
						"description": "No routine found"
					}
				},
				"tags": [
					"iuf.junia"
				]
			}
		},
		"/judges": {
			"post": {
				"description": "Creates a judge",
				"operationId": "judge-create",
				"parameters": [
					{
						"name": "body",
						"in": "body",
						"required": true,
						"description": "The new judge",
						"schema": {
							"$ref": "#/definitions/WritableJudge"
						}
					}
				],
				"responses": {
					"201": {
						"description": "judge created"
					}
				},
				"tags": [
					"iuf.junia"
				]
			},
			"get": {
				"description": "List all judges",
				"operationId": "judge-list",
				"responses": {
					"200": {
						"description": "Array of judges",
						"schema": {
							"$ref": "#/definitions/PagedJudges"
						}
					}
				},
				"tags": [
					"iuf.junia"
				]
			}
		},
		"/judges/{id}": {
			"get": {
				"description": "Reads a judge",
				"operationId": "judge-read",
				"parameters": [
					{
						"name": "id",
						"in": "path",
						"required": true,
						"description": "The judge id",
						"type": "integer"
					}
				],
				"responses": {
					"200": {
						"description": "gets the judge",
						"schema": {
							"$ref": "#/definitions/Judge"
						}
					},
					"400": {
						"description": "Invalid ID supplied"
					},
					"404": {
						"description": "No judge found"
					}
				},
				"tags": [
					"iuf.junia"
				]
			},
			"patch": {
				"description": "Updates a judge",
				"operationId": "judge-update",
				"parameters": [
					{
						"name": "id",
						"in": "path",
						"required": true,
						"description": "The judge id",
						"type": "integer"
					}
				],
				"responses": {
					"200": {
						"description": "judge updated",
						"schema": {
							"$ref": "#/definitions/Judge"
						}
					},
					"400": {
						"description": "Invalid ID supplied"
					},
					"404": {
						"description": "No judge found"
					}
				},
				"tags": [
					"iuf.junia"
				]
			},
			"delete": {
				"description": "Deletes a judge",
				"operationId": "judge-delete",
				"parameters": [
					{
						"name": "id",
						"in": "path",
						"required": true,
						"description": "The judge id",
						"type": "integer"
					}
				],
				"responses": {
					"204": {
						"description": "judge deleted"
					},
					"400": {
						"description": "Invalid ID supplied"
					},
					"404": {
						"description": "No judge found"
					}
				},
				"tags": [
					"iuf.junia"
				]
			}
		},
		"/judges/{id}/relationship/startgroup": {
			"get": {
				"description": "Reads the relationship of judge to startgroup",
				"operationId": "judge-to-startgroup-relationship-read",
				"parameters": [
					{
						"name": "id",
						"in": "path",
						"required": true,
						"description": "The judge id",
						"type": "integer"
					}
				],
				"responses": {
					"400": {
						"description": "Invalid ID supplied"
					},
					"404": {
						"description": "No judge found"
					}
				},
				"tags": [
					"iuf.junia"
				]
			},
			"patch": {
				"description": "Updates the relationship of judge to startgroup",
				"operationId": "judge-to-startgroup-relationship-update",
				"parameters": [
					{
						"name": "id",
						"in": "path",
						"required": true,
						"description": "The judge id",
						"type": "integer"
					}
				],
				"responses": {
					"400": {
						"description": "Invalid ID supplied"
					},
					"404": {
						"description": "No judge found"
					}
				},
				"tags": [
					"iuf.junia"
				]
			}
		},
		"/judges/{id}/relationship/user": {
			"get": {
				"description": "Reads the relationship of judge to user",
				"operationId": "judge-to-user-relationship-read",
				"parameters": [
					{
						"name": "id",
						"in": "path",
						"required": true,
						"description": "The judge id",
						"type": "integer"
					}
				],
				"responses": {
					"400": {
						"description": "Invalid ID supplied"
					},
					"404": {
						"description": "No judge found"
					}
				},
				"tags": [
					"iuf.junia"
				]
			},
			"patch": {
				"description": "Updates the relationship of judge to user",
				"operationId": "judge-to-user-relationship-update",
				"parameters": [
					{
						"name": "id",
						"in": "path",
						"required": true,
						"description": "The judge id",
						"type": "integer"
					}
				],
				"responses": {
					"400": {
						"description": "Invalid ID supplied"
					},
					"404": {
						"description": "No judge found"
					}
				},
				"tags": [
					"iuf.junia"
				]
			}
		},
		"/scores": {
			"post": {
				"description": "Creates a score",
				"operationId": "score-create",
				"parameters": [
					{
						"name": "body",
						"in": "body",
						"required": true,
						"description": "The new score",
						"schema": {
							"$ref": "#/definitions/WritableScore"
						}
					}
				],
				"responses": {
					"201": {
						"description": "score created"
					}
				},
				"tags": [
					"iuf.junia"
				]
			},
			"get": {
				"description": "List all scores",
				"operationId": "score-list",
				"responses": {
					"200": {
						"description": "Array of scores",
						"schema": {
							"$ref": "#/definitions/PagedScores"
						}
					}
				},
				"tags": [
					"iuf.junia"
				]
			}
		},
		"/scores/{id}": {
			"get": {
				"description": "Reads a score",
				"operationId": "score-read",
				"parameters": [
					{
						"name": "id",
						"in": "path",
						"required": true,
						"description": "The score id",
						"type": "integer"
					}
				],
				"responses": {
					"200": {
						"description": "gets the score",
						"schema": {
							"$ref": "#/definitions/Score"
						}
					},
					"400": {
						"description": "Invalid ID supplied"
					},
					"404": {
						"description": "No score found"
					}
				},
				"tags": [
					"iuf.junia"
				]
			},
			"patch": {
				"description": "Updates a score",
				"operationId": "score-update",
				"parameters": [
					{
						"name": "id",
						"in": "path",
						"required": true,
						"description": "The score id",
						"type": "integer"
					}
				],
				"responses": {
					"200": {
						"description": "score updated",
						"schema": {
							"$ref": "#/definitions/Score"
						}
					},
					"400": {
						"description": "Invalid ID supplied"
					},
					"404": {
						"description": "No score found"
					}
				},
				"tags": [
					"iuf.junia"
				]
			},
			"delete": {
				"description": "Deletes a score",
				"operationId": "score-delete",
				"parameters": [
					{
						"name": "id",
						"in": "path",
						"required": true,
						"description": "The score id",
						"type": "integer"
					}
				],
				"responses": {
					"204": {
						"description": "score deleted"
					},
					"400": {
						"description": "Invalid ID supplied"
					},
					"404": {
						"description": "No score found"
					}
				},
				"tags": [
					"iuf.junia"
				]
			}
		},
		"/scores/{id}/relationship/routine": {
			"get": {
				"description": "Reads the relationship of score to routine",
				"operationId": "score-to-routine-relationship-read",
				"parameters": [
					{
						"name": "id",
						"in": "path",
						"required": true,
						"description": "The score id",
						"type": "integer"
					}
				],
				"responses": {
					"400": {
						"description": "Invalid ID supplied"
					},
					"404": {
						"description": "No score found"
					}
				},
				"tags": [
					"iuf.junia"
				]
			},
			"patch": {
				"description": "Updates the relationship of score to routine",
				"operationId": "score-to-routine-relationship-update",
				"parameters": [
					{
						"name": "id",
						"in": "path",
						"required": true,
						"description": "The score id",
						"type": "integer"
					}
				],
				"responses": {
					"400": {
						"description": "Invalid ID supplied"
					},
					"404": {
						"description": "No score found"
					}
				},
				"tags": [
					"iuf.junia"
				]
			}
		},
		"/scores/{id}/relationship/judge": {
			"get": {
				"description": "Reads the relationship of score to judge",
				"operationId": "score-to-judge-relationship-read",
				"parameters": [
					{
						"name": "id",
						"in": "path",
						"required": true,
						"description": "The score id",
						"type": "integer"
					}
				],
				"responses": {
					"400": {
						"description": "Invalid ID supplied"
					},
					"404": {
						"description": "No score found"
					}
				},
				"tags": [
					"iuf.junia"
				]
			},
			"patch": {
				"description": "Updates the relationship of score to judge",
				"operationId": "score-to-judge-relationship-update",
				"parameters": [
					{
						"name": "id",
						"in": "path",
						"required": true,
						"description": "The score id",
						"type": "integer"
					}
				],
				"responses": {
					"400": {
						"description": "Invalid ID supplied"
					},
					"404": {
						"description": "No score found"
					}
				},
				"tags": [
					"iuf.junia"
				]
			}
		},
		"/performance_scores": {
			"post": {
				"description": "Creates a performance-score",
				"operationId": "performance_score-create",
				"parameters": [
					{
						"name": "body",
						"in": "body",
						"required": true,
						"description": "The new performance_score",
						"schema": {
							"$ref": "#/definitions/WritablePerformanceScore"
						}
					}
				],
				"responses": {
					"201": {
						"description": "performance_score created"
					}
				},
				"tags": [
					"iuf.junia"
				]
			},
			"get": {
				"description": "List all performance-scores",
				"operationId": "performance_score-list",
				"responses": {
					"200": {
						"description": "Array of performance_scores",
						"schema": {
							"$ref": "#/definitions/PagedPerformanceScores"
						}
					}
				},
				"tags": [
					"iuf.junia"
				]
			}
		},
		"/performance_scores/{id}": {
			"get": {
				"description": "Reads a performance-score",
				"operationId": "performance_score-read",
				"parameters": [
					{
						"name": "id",
						"in": "path",
						"required": true,
						"description": "The performance_score id",
						"type": "integer"
					}
				],
				"responses": {
					"200": {
						"description": "gets the performance_score",
						"schema": {
							"$ref": "#/definitions/PerformanceScore"
						}
					},
					"400": {
						"description": "Invalid ID supplied"
					},
					"404": {
						"description": "No performance_score found"
					}
				},
				"tags": [
					"iuf.junia"
				]
			},
			"patch": {
				"description": "Updates a performance-score",
				"operationId": "performance_score-update",
				"parameters": [
					{
						"name": "id",
						"in": "path",
						"required": true,
						"description": "The performance_score id",
						"type": "integer"
					}
				],
				"responses": {
					"200": {
						"description": "performance_score updated",
						"schema": {
							"$ref": "#/definitions/PerformanceScore"
						}
					},
					"400": {
						"description": "Invalid ID supplied"
					},
					"404": {
						"description": "No performance_score found"
					}
				},
				"tags": [
					"iuf.junia"
				]
			},
			"delete": {
				"description": "Deletes a performance-score",
				"operationId": "performance_score-delete",
				"parameters": [
					{
						"name": "id",
						"in": "path",
						"required": true,
						"description": "The performance_score id",
						"type": "integer"
					}
				],
				"responses": {
					"204": {
						"description": "performance_score deleted"
					},
					"400": {
						"description": "Invalid ID supplied"
					},
					"404": {
						"description": "No performance_score found"
					}
				},
				"tags": [
					"iuf.junia"
				]
			}
		},
		"/performance_scores/{id}/relationship/routine": {
			"get": {
				"description": "Reads the relationship of performance_score to routine",
				"operationId": "performance_score-to-routine-relationship-read",
				"parameters": [
					{
						"name": "id",
						"in": "path",
						"required": true,
						"description": "The performance_score id",
						"type": "integer"
					}
				],
				"responses": {
					"400": {
						"description": "Invalid ID supplied"
					},
					"404": {
						"description": "No performance_score found"
					}
				},
				"tags": [
					"iuf.junia"
				]
			},
			"patch": {
				"description": "Updates the relationship of performance_score to routine",
				"operationId": "performance_score-to-routine-relationship-update",
				"parameters": [
					{
						"name": "id",
						"in": "path",
						"required": true,
						"description": "The performance_score id",
						"type": "integer"
					}
				],
				"responses": {
					"400": {
						"description": "Invalid ID supplied"
					},
					"404": {
						"description": "No performance_score found"
					}
				},
				"tags": [
					"iuf.junia"
				]
			}
		},
		"/performance_scores/{id}/relationship/judge": {
			"get": {
				"description": "Reads the relationship of performance_score to judge",
				"operationId": "performance_score-to-judge-relationship-read",
				"parameters": [
					{
						"name": "id",
						"in": "path",
						"required": true,
						"description": "The performance_score id",
						"type": "integer"
					}
				],
				"responses": {
					"400": {
						"description": "Invalid ID supplied"
					},
					"404": {
						"description": "No performance_score found"
					}
				},
				"tags": [
					"iuf.junia"
				]
			},
			"patch": {
				"description": "Updates the relationship of performance_score to judge",
				"operationId": "performance_score-to-judge-relationship-update",
				"parameters": [
					{
						"name": "id",
						"in": "path",
						"required": true,
						"description": "The performance_score id",
						"type": "integer"
					}
				],
				"responses": {
					"400": {
						"description": "Invalid ID supplied"
					},
					"404": {
						"description": "No performance_score found"
					}
				},
				"tags": [
					"iuf.junia"
				]
			}
		},
		"/performance_statisticss": {
			"post": {
				"description": "Creates a performance-statistics",
				"operationId": "performance_statistics-create",
				"parameters": [
					{
						"name": "body",
						"in": "body",
						"required": true,
						"description": "The new performance_statistics",
						"schema": {
							"$ref": "#/definitions/WritablePerformanceStatistics"
						}
					}
				],
				"responses": {
					"201": {
						"description": "performance_statistics created"
					}
				},
				"tags": [
					"iuf.junia"
				]
			},
			"get": {
				"description": "List all performance-statisticss",
				"operationId": "performance_statistics-list",
				"responses": {
					"200": {
						"description": "Array of performance_statisticss",
						"schema": {
							"$ref": "#/definitions/PagedPerformanceStatisticss"
						}
					}
				},
				"tags": [
					"iuf.junia"
				]
			}
		},
		"/performance_statisticss/{id}": {
			"get": {
				"description": "Reads a performance-statistics",
				"operationId": "performance_statistics-read",
				"parameters": [
					{
						"name": "id",
						"in": "path",
						"required": true,
						"description": "The performance_statistics id",
						"type": "integer"
					}
				],
				"responses": {
					"200": {
						"description": "gets the performance_statistics",
						"schema": {
							"$ref": "#/definitions/PerformanceStatistics"
						}
					},
					"400": {
						"description": "Invalid ID supplied"
					},
					"404": {
						"description": "No performance_statistics found"
					}
				},
				"tags": [
					"iuf.junia"
				]
			},
			"patch": {
				"description": "Updates a performance-statistics",
				"operationId": "performance_statistics-update",
				"parameters": [
					{
						"name": "id",
						"in": "path",
						"required": true,
						"description": "The performance_statistics id",
						"type": "integer"
					}
				],
				"responses": {
					"200": {
						"description": "performance_statistics updated",
						"schema": {
							"$ref": "#/definitions/PerformanceStatistics"
						}
					},
					"400": {
						"description": "Invalid ID supplied"
					},
					"404": {
						"description": "No performance_statistics found"
					}
				},
				"tags": [
					"iuf.junia"
				]
			},
			"delete": {
				"description": "Deletes a performance-statistics",
				"operationId": "performance_statistics-delete",
				"parameters": [
					{
						"name": "id",
						"in": "path",
						"required": true,
						"description": "The performance_statistics id",
						"type": "integer"
					}
				],
				"responses": {
					"204": {
						"description": "performance_statistics deleted"
					},
					"400": {
						"description": "Invalid ID supplied"
					},
					"404": {
						"description": "No performance_statistics found"
					}
				},
				"tags": [
					"iuf.junia"
				]
			}
		}
	},
	"definitions": {
		"PagedMeta": {
			"type": "object",
			"properties": {
				"total": {
					"type": "integer"
				},
				"first": {
					"type": "integer"
				},
				"next": {
					"type": "integer"
				},
				"previous": {
					"type": "integer"
				},
				"last": {
					"type": "integer"
				}
			}
		},
		"ResourceIdentifier": {
			"type": "object",
			"properties": {
				"id": {
					"type": "string"
				},
				"type": {
					"type": "string"
				}
			}
		},
		"PagedCompetitions": {
			"type": "object",
			"properties": {
				"data": {
					"type": "array",
					"items": {
						"$ref": "#/definitions/Competition"
					}
				},
				"meta": {
					"$ref": "#/definitions/PagedMeta"
				}
			}
		},
		"WritableCompetition": {
			"type": "object",
			"properties": {
				"data": {
					"type": "object",
					"properties": {
						"id": {
							"type": "string"
						},
						"type": {
							"type": "string"
						},
						"attributes": {
							"type": "object",
							"properties": {
								"label": {
									"type": "string"
								}
							}
						}
					}
				}
			}
		},
		"Competition": {
			"type": "object",
			"properties": {
				"links": {
					"type": "object",
					"properties": {
						"self": {
							"type": "string"
						}
					}
				},
				"data": {
					"type": "object",
					"properties": {
						"id": {
							"type": "string"
						},
						"type": {
							"type": "string"
						},
						"attributes": {
							"type": "object",
							"properties": {
								"label": {
									"type": "string"
								}
							}
						}
					}
				}
			}
		},
		"PagedStartgroups": {
			"type": "object",
			"properties": {
				"data": {
					"type": "array",
					"items": {
						"$ref": "#/definitions/Startgroup"
					}
				},
				"meta": {
					"$ref": "#/definitions/PagedMeta"
				}
			}
		},
		"WritableStartgroup": {
			"type": "object",
			"properties": {
				"data": {
					"type": "object",
					"properties": {
						"id": {
							"type": "string"
						},
						"type": {
							"type": "string"
						},
						"attributes": {
							"type": "object",
							"properties": {
								"name": {
									"type": "string"
								},
								"competition_id": {
									"type": "integer"
								},
								"event_id": {
									"type": "integer"
								}
							}
						},
						"relationships": {
							"type": "object",
							"properties": {
								"competition": {
									"type": "object",
									"properties": {
										"data": {
											"type": "object",
											"properties": {
												"id": {
													"type": "string"
												},
												"type": {
													"type": "string"
												}
											}
										}
									}
								},
								"event": {
									"type": "object",
									"properties": {
										"data": {
											"type": "object",
											"properties": {
												"id": {
													"type": "string"
												},
												"type": {
													"type": "string"
												}
											}
										}
									}
								}
							}
						}
					}
				}
			}
		},
		"Startgroup": {
			"type": "object",
			"properties": {
				"links": {
					"type": "object",
					"properties": {
						"self": {
							"type": "string"
						}
					}
				},
				"data": {
					"type": "object",
					"properties": {
						"id": {
							"type": "string"
						},
						"type": {
							"type": "string"
						},
						"attributes": {
							"type": "object",
							"properties": {
								"name": {
									"type": "string"
								},
								"competition_id": {
									"type": "integer"
								},
								"event_id": {
									"type": "integer"
								}
							}
						},
						"relationships": {
							"type": "object",
							"properties": {
								"competition": {
									"type": "object",
									"properties": {
										"links": {
											"type": "object",
											"properties": {
												"self": {
													"type": "string"
												}
											}
										},
										"data": {
											"type": "object",
											"properties": {
												"id": {
													"type": "string"
												},
												"type": {
													"type": "string"
												}
											}
										}
									}
								},
								"event": {
									"type": "object",
									"properties": {
										"links": {
											"type": "object",
											"properties": {
												"self": {
													"type": "string"
												}
											}
										},
										"data": {
											"type": "object",
											"properties": {
												"id": {
													"type": "string"
												},
												"type": {
													"type": "string"
												}
											}
										}
									}
								}
							}
						}
					}
				}
			}
		},
		"PagedRoutines": {
			"type": "object",
			"properties": {
				"data": {
					"type": "array",
					"items": {
						"$ref": "#/definitions/Routine"
					}
				},
				"meta": {
					"$ref": "#/definitions/PagedMeta"
				}
			}
		},
		"WritableRoutine": {
			"type": "object",
			"properties": {
				"data": {
					"type": "object",
					"properties": {
						"id": {
							"type": "string"
						},
						"type": {
							"type": "string"
						},
						"attributes": {
							"type": "object",
							"properties": {
								"name": {
									"type": "string"
								},
								"startgroup_id": {
									"type": "integer"
								},
								"performance_total_statistics_id": {
									"type": "integer"
								},
								"performance_execution_statistics_id": {
									"type": "integer"
								},
								"performance_choreography_statistics_id": {
									"type": "integer"
								},
								"performance_music_and_timing_statistics_id": {
									"type": "integer"
								}
							}
						},
						"relationships": {
							"type": "object",
							"properties": {
								"startgroup": {
									"type": "object",
									"properties": {
										"data": {
											"type": "object",
											"properties": {
												"id": {
													"type": "string"
												},
												"type": {
													"type": "string"
												}
											}
										}
									}
								},
								"performance-statistics": {
									"type": "object",
									"properties": {
										"data": {
											"type": "object",
											"properties": {
												"id": {
													"type": "string"
												},
												"type": {
													"type": "string"
												}
											}
										}
									}
								}
							}
						}
					}
				}
			}
		},
		"Routine": {
			"type": "object",
			"properties": {
				"links": {
					"type": "object",
					"properties": {
						"self": {
							"type": "string"
						}
					}
				},
				"data": {
					"type": "object",
					"properties": {
						"id": {
							"type": "string"
						},
						"type": {
							"type": "string"
						},
						"attributes": {
							"type": "object",
							"properties": {
								"name": {
									"type": "string"
								},
								"startgroup_id": {
									"type": "integer"
								},
								"performance_total_statistics_id": {
									"type": "integer"
								},
								"performance_execution_statistics_id": {
									"type": "integer"
								},
								"performance_choreography_statistics_id": {
									"type": "integer"
								},
								"performance_music_and_timing_statistics_id": {
									"type": "integer"
								}
							}
						},
						"relationships": {
							"type": "object",
							"properties": {
								"startgroup": {
									"type": "object",
									"properties": {
										"links": {
											"type": "object",
											"properties": {
												"self": {
													"type": "string"
												}
											}
										},
										"data": {
											"type": "object",
											"properties": {
												"id": {
													"type": "string"
												},
												"type": {
													"type": "string"
												}
											}
										}
									}
								},
								"performance-statistics": {
									"type": "object",
									"properties": {
										"links": {
											"type": "object",
											"properties": {
												"self": {
													"type": "string"
												}
											}
										},
										"data": {
											"type": "object",
											"properties": {
												"id": {
													"type": "string"
												},
												"type": {
													"type": "string"
												}
											}
										}
									}
								}
							}
						}
					}
				}
			}
		},
		"PagedJudges": {
			"type": "object",
			"properties": {
				"data": {
					"type": "array",
					"items": {
						"$ref": "#/definitions/Judge"
					}
				},
				"meta": {
					"$ref": "#/definitions/PagedMeta"
				}
			}
		},
		"WritableJudge": {
			"type": "object",
			"properties": {
				"data": {
					"type": "object",
					"properties": {
						"id": {
							"type": "string"
						},
						"type": {
							"type": "string"
						},
						"attributes": {
							"type": "object",
							"properties": {
								"position": {
									"type": "string"
								},
								"startgroup_id": {
									"type": "integer"
								},
								"user_id": {
									"type": "integer"
								}
							}
						},
						"relationships": {
							"type": "object",
							"properties": {
								"startgroup": {
									"type": "object",
									"properties": {
										"data": {
											"type": "object",
											"properties": {
												"id": {
													"type": "string"
												},
												"type": {
													"type": "string"
												}
											}
										}
									}
								},
								"user": {
									"type": "object",
									"properties": {
										"data": {
											"type": "object",
											"properties": {
												"id": {
													"type": "string"
												},
												"type": {
													"type": "string"
												}
											}
										}
									}
								}
							}
						}
					}
				}
			}
		},
		"Judge": {
			"type": "object",
			"properties": {
				"links": {
					"type": "object",
					"properties": {
						"self": {
							"type": "string"
						}
					}
				},
				"data": {
					"type": "object",
					"properties": {
						"id": {
							"type": "string"
						},
						"type": {
							"type": "string"
						},
						"attributes": {
							"type": "object",
							"properties": {
								"position": {
									"type": "string"
								},
								"startgroup_id": {
									"type": "integer"
								},
								"user_id": {
									"type": "integer"
								}
							}
						},
						"relationships": {
							"type": "object",
							"properties": {
								"startgroup": {
									"type": "object",
									"properties": {
										"links": {
											"type": "object",
											"properties": {
												"self": {
													"type": "string"
												}
											}
										},
										"data": {
											"type": "object",
											"properties": {
												"id": {
													"type": "string"
												},
												"type": {
													"type": "string"
												}
											}
										}
									}
								},
								"user": {
									"type": "object",
									"properties": {
										"links": {
											"type": "object",
											"properties": {
												"self": {
													"type": "string"
												}
											}
										},
										"data": {
											"type": "object",
											"properties": {
												"id": {
													"type": "string"
												},
												"type": {
													"type": "string"
												}
											}
										}
									}
								}
							}
						}
					}
				}
			}
		},
		"PagedScores": {
			"type": "object",
			"properties": {
				"data": {
					"type": "array",
					"items": {
						"$ref": "#/definitions/Score"
					}
				},
				"meta": {
					"$ref": "#/definitions/PagedMeta"
				}
			}
		},
		"WritableScore": {
			"type": "object",
			"properties": {
				"data": {
					"type": "object",
					"properties": {
						"id": {
							"type": "string"
						},
						"type": {
							"type": "string"
						},
						"attributes": {
							"type": "object",
							"properties": {
								"routine_id": {
									"type": "integer"
								},
								"judge_id": {
									"type": "integer"
								},
								"total": {
									"type": "double"
								},
								"descendant_class": {
									"type": "string"
								}
							}
						},
						"relationships": {
							"type": "object",
							"properties": {
								"routine": {
									"type": "object",
									"properties": {
										"data": {
											"type": "object",
											"properties": {
												"id": {
													"type": "string"
												},
												"type": {
													"type": "string"
												}
											}
										}
									}
								},
								"judge": {
									"type": "object",
									"properties": {
										"data": {
											"type": "object",
											"properties": {
												"id": {
													"type": "string"
												},
												"type": {
													"type": "string"
												}
											}
										}
									}
								}
							}
						}
					}
				}
			}
		},
		"Score": {
			"type": "object",
			"properties": {
				"links": {
					"type": "object",
					"properties": {
						"self": {
							"type": "string"
						}
					}
				},
				"data": {
					"type": "object",
					"properties": {
						"id": {
							"type": "string"
						},
						"type": {
							"type": "string"
						},
						"attributes": {
							"type": "object",
							"properties": {
								"routine_id": {
									"type": "integer"
								},
								"judge_id": {
									"type": "integer"
								},
								"total": {
									"type": "double"
								},
								"descendant_class": {
									"type": "string"
								}
							}
						},
						"relationships": {
							"type": "object",
							"properties": {
								"routine": {
									"type": "object",
									"properties": {
										"links": {
											"type": "object",
											"properties": {
												"self": {
													"type": "string"
												}
											}
										},
										"data": {
											"type": "object",
											"properties": {
												"id": {
													"type": "string"
												},
												"type": {
													"type": "string"
												}
											}
										}
									}
								},
								"judge": {
									"type": "object",
									"properties": {
										"links": {
											"type": "object",
											"properties": {
												"self": {
													"type": "string"
												}
											}
										},
										"data": {
											"type": "object",
											"properties": {
												"id": {
													"type": "string"
												},
												"type": {
													"type": "string"
												}
											}
										}
									}
								}
							}
						}
					}
				}
			}
		},
		"PagedPerformanceScores": {
			"type": "object",
			"properties": {
				"data": {
					"type": "array",
					"items": {
						"$ref": "#/definitions/PerformanceScore"
					}
				},
				"meta": {
					"$ref": "#/definitions/PagedMeta"
				}
			}
		},
		"WritablePerformanceScore": {
			"type": "object",
			"properties": {
				"data": {
					"type": "object",
					"properties": {
						"id": {
							"type": "string"
						},
						"type": {
							"type": "string"
						},
						"attributes": {
							"type": "object",
							"properties": {
								"execution": {
									"type": "double"
								},
								"choreography": {
									"type": "double"
								},
								"music_and_timing": {
									"type": "double"
								},
								"routine_id": {
									"type": "integer"
								},
								"judge_id": {
									"type": "integer"
								},
								"total": {
									"type": "double"
								}
							}
						},
						"relationships": {
							"type": "object",
							"properties": {
								"routine": {
									"type": "object",
									"properties": {
										"data": {
											"type": "object",
											"properties": {
												"id": {
													"type": "string"
												},
												"type": {
													"type": "string"
												}
											}
										}
									}
								},
								"judge": {
									"type": "object",
									"properties": {
										"data": {
											"type": "object",
											"properties": {
												"id": {
													"type": "string"
												},
												"type": {
													"type": "string"
												}
											}
										}
									}
								}
							}
						}
					}
				}
			}
		},
		"PerformanceScore": {
			"type": "object",
			"properties": {
				"links": {
					"type": "object",
					"properties": {
						"self": {
							"type": "string"
						}
					}
				},
				"data": {
					"type": "object",
					"properties": {
						"id": {
							"type": "string"
						},
						"type": {
							"type": "string"
						},
						"attributes": {
							"type": "object",
							"properties": {
								"execution": {
									"type": "double"
								},
								"choreography": {
									"type": "double"
								},
								"music_and_timing": {
									"type": "double"
								},
								"routine_id": {
									"type": "integer"
								},
								"judge_id": {
									"type": "integer"
								},
								"total": {
									"type": "double"
								}
							}
						},
						"relationships": {
							"type": "object",
							"properties": {
								"routine": {
									"type": "object",
									"properties": {
										"links": {
											"type": "object",
											"properties": {
												"self": {
													"type": "string"
												}
											}
										},
										"data": {
											"type": "object",
											"properties": {
												"id": {
													"type": "string"
												},
												"type": {
													"type": "string"
												}
											}
										}
									}
								},
								"judge": {
									"type": "object",
									"properties": {
										"links": {
											"type": "object",
											"properties": {
												"self": {
													"type": "string"
												}
											}
										},
										"data": {
											"type": "object",
											"properties": {
												"id": {
													"type": "string"
												},
												"type": {
													"type": "string"
												}
											}
										}
									}
								}
							}
						}
					}
				}
			}
		},
		"PagedPerformanceStatisticss": {
			"type": "object",
			"properties": {
				"data": {
					"type": "array",
					"items": {
						"$ref": "#/definitions/PerformanceStatistics"
					}
				},
				"meta": {
					"$ref": "#/definitions/PagedMeta"
				}
			}
		},
		"WritablePerformanceStatistics": {
			"type": "object",
			"properties": {
				"data": {
					"type": "object",
					"properties": {
						"id": {
							"type": "string"
						},
						"type": {
							"type": "string"
						},
						"attributes": {
							"type": "object",
							"properties": {
								"min": {
									"type": "double"
								},
								"max": {
									"type": "double"
								},
								"range": {
									"type": "double"
								},
								"average": {
									"type": "double"
								},
								"standard_deviation": {
									"type": "double"
								},
								"variance": {
									"type": "double"
								}
							}
						}
					}
				}
			}
		},
		"PerformanceStatistics": {
			"type": "object",
			"properties": {
				"links": {
					"type": "object",
					"properties": {
						"self": {
							"type": "string"
						}
					}
				},
				"data": {
					"type": "object",
					"properties": {
						"id": {
							"type": "string"
						},
						"type": {
							"type": "string"
						},
						"attributes": {
							"type": "object",
							"properties": {
								"min": {
									"type": "double"
								},
								"max": {
									"type": "double"
								},
								"range": {
									"type": "double"
								},
								"average": {
									"type": "double"
								},
								"standard_deviation": {
									"type": "double"
								},
								"variance": {
									"type": "double"
								}
							}
						}
					}
				}
			}
		}
	},
	"tags": [
		{
			"name": "iuf.junia"
		}
	]
}